{
  "version": "0.4.15",
  "flags": {},
  "shapes": [
    {
      "label": "红笔",
      "text": "",
      "points": [
        [
          362.0,
          73.0
        ],
        [
          362.0,
          75.0
        ],
        [
          360.0,
          78.0
        ],
        [
          360.0,
          82.0
        ],
        [
          368.0,
          89.0
        ],
        [
          368.0,
          91.0
        ],
        [
          371.0,
          91.0
        ],
        [
          373.0,
          93.0
        ],
        [
          373.0,
          94.0
        ],
        [
          378.0,
          99.0
        ],
        [
          380.0,
          103.0
        ],
        [
          383.0,
          104.0
        ],
        [
          392.0,
          113.0
        ],
        [
          396.0,
          115.0
        ],
        [
          400.0,
          119.0
        ],
        [
          406.0,
          121.0
        ],
        [
          409.0,
          126.0
        ],
        [
          410.0,
          126.0
        ],
        [
          414.0,
          130.0
        ],
        [
          419.0,
          132.0
        ],
        [
          422.0,
          137.0
        ],
        [
          430.0,
          141.0
        ],
        [
          435.0,
          147.0
        ],
        [
          436.0,
          147.0
        ],
        [
          450.0,
          159.0
        ],
        [
          453.0,
          160.0
        ],
        [
          457.0,
          165.0
        ],
        [
          461.0,
          166.0
        ],
        [
          467.0,
          173.0
        ],
        [
          473.0,
          176.0
        ],
        [
          475.0,
          178.0
        ],
        [
          475.0,
          181.0
        ],
        [
          487.0,
          188.0
        ],
        [
          490.0,
          193.0
        ],
        [
          492.0,
          193.0
        ],
        [
          495.0,
          195.0
        ],
        [
          508.0,
          207.0
        ],
        [
          514.0,
          211.0
        ],
        [
          518.0,
          215.0
        ],
        [
          521.0,
          220.0
        ],
        [
          523.0,
          220.0
        ],
        [
          526.0,
          222.0
        ],
        [
          529.0,
          222.0
        ],
        [
          531.0,
          226.0
        ],
        [
          536.0,
          227.0
        ],
        [
          543.0,
          232.0
        ],
        [
          545.0,
          232.0
        ],
        [
          549.0,
          234.0
        ],
        [
          553.0,
          234.0
        ],
        [
          556.0,
          236.0
        ],
        [
          557.0,
          236.0
        ],
        [
          560.0,
          233.0
        ],
        [
          560.0,
          229.0
        ],
        [
          557.0,
          223.0
        ],
        [
          539.0,
          202.0
        ],
        [
          535.0,
          200.0
        ],
        [
          522.0,
          188.0
        ],
        [
          517.0,
          185.0
        ],
        [
          509.0,
          177.0
        ],
        [
          505.0,
          175.0
        ],
        [
          501.0,
          171.0
        ],
        [
          495.0,
          167.0
        ],
        [
          483.0,
          155.0
        ],
        [
          480.0,
          154.0
        ],
        [
          467.0,
          143.0
        ],
        [
          458.0,
          138.0
        ],
        [
          453.0,
          133.0
        ],
        [
          453.0,
          130.0
        ],
        [
          455.0,
          128.0
        ],
        [
          455.0,
          126.0
        ],
        [
          456.0,
          125.0
        ],
        [
          453.0,
          121.0
        ],
        [
          447.0,
          119.0
        ],
        [
          442.0,
          114.0
        ],
        [
          442.0,
          113.0
        ],
        [
          434.0,
          108.0
        ],
        [
          419.0,
          94.0
        ],
        [
          418.0,
          94.0
        ],
        [
          414.0,
          90.0
        ],
        [
          408.0,
          86.0
        ],
        [
          401.0,
          83.0
        ],
        [
          396.0,
          77.0
        ],
        [
          394.0,
          76.0
        ],
        [
          390.0,
          76.0
        ],
        [
          388.0,
          79.0
        ],
        [
          379.0,
          79.0
        ],
        [
          369.0,
          71.0
        ],
        [
          364.0,
          71.0
        ]
      ],
      "group_id": null,
      "shape_type": "polygon",
      "flags": {}
    },
    {
      "label": "旺旺雪饼",
      "text": "",
      "points": [
        [
          265.0,
          33.0
        ],
        [
          259.0,
          36.0
        ],
        [
          247.0,
          45.0
        ],
        [
          243.0,
          46.0
        ],
        [
          240.0,
          49.0
        ],
        [
          226.0,
          56.0
        ],
        [
          217.0,
          63.0
        ],
        [
          209.0,
          67.0
        ],
        [
          192.0,
          82.0
        ],
        [
          183.0,
          85.0
        ],
        [
          167.0,
          88.0
        ],
        [
          152.0,
          93.0
        ],
        [
          125.0,
          107.0
        ],
        [
          121.0,
          108.0
        ],
        [
          116.0,
          111.0
        ],
        [
          114.0,
          114.0
        ],
        [
          120.0,
          124.0
        ],
        [
          122.0,
          124.0
        ],
        [
          124.0,
          126.0
        ],
        [
          126.0,
          125.0
        ],
        [
          129.0,
          126.0
        ],
        [
          129.0,
          128.0
        ],
        [
          127.0,
          130.0
        ],
        [
          130.0,
          133.0
        ],
        [
          133.0,
          132.0
        ],
        [
          135.0,
          134.0
        ],
        [
          136.0,
          138.0
        ],
        [
          143.0,
          142.0
        ],
        [
          143.0,
          144.0
        ],
        [
          146.0,
          147.0
        ],
        [
          149.0,
          154.0
        ],
        [
          153.0,
          159.0
        ],
        [
          156.0,
          160.0
        ],
        [
          158.0,
          168.0
        ],
        [
          162.0,
          173.0
        ],
        [
          162.0,
          177.0
        ],
        [
          158.0,
          178.0
        ],
        [
          161.0,
          178.0
        ],
        [
          164.0,
          180.0
        ],
        [
          166.0,
          188.0
        ],
        [
          170.0,
          193.0
        ],
        [
          170.0,
          195.0
        ],
        [
          172.0,
          197.0
        ],
        [
          172.0,
          200.0
        ],
        [
          179.0,
          207.0
        ],
        [
          181.0,
          212.0
        ],
        [
          192.0,
          224.0
        ],
        [
          192.0,
          234.0
        ],
        [
          196.0,
          242.0
        ],
        [
          196.0,
          245.0
        ],
        [
          199.0,
          249.0
        ],
        [
          198.0,
          250.0
        ],
        [
          199.0,
          259.0
        ],
        [
          203.0,
          265.0
        ],
        [
          204.0,
          274.0
        ],
        [
          206.0,
          276.0
        ],
        [
          217.0,
          274.0
        ],
        [
          222.0,
          271.0
        ],
        [
          230.0,
          269.0
        ],
        [
          245.0,
          262.0
        ],
        [
          258.0,
          253.0
        ],
        [
          285.0,
          246.0
        ],
        [
          292.0,
          242.0
        ],
        [
          301.0,
          240.0
        ],
        [
          303.0,
          238.0
        ],
        [
          317.0,
          232.0
        ],
        [
          320.0,
          232.0
        ],
        [
          334.0,
          227.0
        ],
        [
          343.0,
          226.0
        ],
        [
          346.0,
          223.0
        ],
        [
          343.0,
          215.0
        ],
        [
          334.0,
          206.0
        ],
        [
          332.0,
          199.0
        ],
        [
          330.0,
          197.0
        ],
        [
          324.0,
          196.0
        ],
        [
          320.0,
          191.0
        ],
        [
          319.0,
          186.0
        ],
        [
          316.0,
          181.0
        ],
        [
          316.0,
          178.0
        ],
        [
          312.0,
          172.0
        ],
        [
          310.0,
          164.0
        ],
        [
          301.0,
          149.0
        ],
        [
          300.0,
          142.0
        ],
        [
          287.0,
          116.0
        ],
        [
          282.0,
          101.0
        ],
        [
          282.0,
          97.0
        ],
        [
          275.0,
          80.0
        ],
        [
          276.0,
          76.0
        ],
        [
          275.0,
          75.0
        ],
        [
          274.0,
          65.0
        ],
        [
          268.0,
          56.0
        ],
        [
          268.0,
          52.0
        ],
        [
          271.0,
          49.0
        ],
        [
          272.0,
          43.0
        ],
        [
          269.0,
          36.0
        ]
      ],
      "group_id": null,
      "shape_type": "polygon",
      "flags": {}
    },
    {
      "label": "黑笔",
      "text": "",
      "points": [
        [
          26.0,
          360.0
        ],
        [
          24.0,
          364.0
        ],
        [
          24.0,
          366.0
        ],
        [
          23.0,
          367.0
        ],
        [
          23.0,
          370.0
        ],
        [
          24.0,
          371.0
        ],
        [
          28.0,
          372.0
        ],
        [
          36.0,
          376.0
        ],
        [
          38.0,
          378.0
        ],
        [
          44.0,
          380.0
        ],
        [
          46.0,
          382.0
        ],
        [
          52.0,
          385.0
        ],
        [
          54.0,
          385.0
        ],
        [
          60.0,
          388.0
        ],
        [
          66.0,
          389.0
        ],
        [
          72.0,
          392.0
        ],
        [
          75.0,
          395.0
        ],
        [
          77.0,
          395.0
        ],
        [
          87.0,
          400.0
        ],
        [
          93.0,
          401.0
        ],
        [
          99.0,
          405.0
        ],
        [
          104.0,
          406.0
        ],
        [
          106.0,
          408.0
        ],
        [
          111.0,
          410.0
        ],
        [
          115.0,
          414.0
        ],
        [
          117.0,
          414.0
        ],
        [
          119.0,
          416.0
        ],
        [
          121.0,
          416.0
        ],
        [
          126.0,
          419.0
        ],
        [
          128.0,
          419.0
        ],
        [
          130.0,
          421.0
        ],
        [
          132.0,
          421.0
        ],
        [
          137.0,
          424.0
        ],
        [
          139.0,
          424.0
        ],
        [
          141.0,
          426.0
        ],
        [
          151.0,
          431.0
        ],
        [
          153.0,
          431.0
        ],
        [
          160.0,
          435.0
        ],
        [
          165.0,
          436.0
        ],
        [
          176.0,
          442.0
        ],
        [
          178.0,
          442.0
        ],
        [
          184.0,
          445.0
        ],
        [
          186.0,
          447.0
        ],
        [
          188.0,
          447.0
        ],
        [
          192.0,
          449.0
        ],
        [
          196.0,
          452.0
        ],
        [
          201.0,
          453.0
        ],
        [
          206.0,
          456.0
        ],
        [
          208.0,
          456.0
        ],
        [
          213.0,
          459.0
        ],
        [
          215.0,
          459.0
        ],
        [
          219.0,
          462.0
        ],
        [
          221.0,
          461.0
        ],
        [
          223.0,
          457.0
        ],
        [
          224.0,
          448.0
        ],
        [
          223.0,
          446.0
        ],
        [
          213.0,
          441.0
        ],
        [
          211.0,
          439.0
        ],
        [
          209.0,
          439.0
        ],
        [
          198.0,
          433.0
        ],
        [
          196.0,
          433.0
        ],
        [
          194.0,
          431.0
        ],
        [
          192.0,
          431.0
        ],
        [
          188.0,
          428.0
        ],
        [
          186.0,
          428.0
        ],
        [
          181.0,
          425.0
        ],
        [
          179.0,
          425.0
        ],
        [
          164.0,
          417.0
        ],
        [
          162.0,
          417.0
        ],
        [
          157.0,
          414.0
        ],
        [
          155.0,
          414.0
        ],
        [
          147.0,
          410.0
        ],
        [
          145.0,
          408.0
        ],
        [
          143.0,
          408.0
        ],
        [
          113.0,
          393.0
        ],
        [
          111.0,
          391.0
        ],
        [
          109.0,
          391.0
        ],
        [
          107.0,
          389.0
        ],
        [
          101.0,
          386.0
        ],
        [
          99.0,
          386.0
        ],
        [
          98.0,
          385.0
        ],
        [
          96.0,
          385.0
        ],
        [
          92.0,
          383.0
        ],
        [
          89.0,
          380.0
        ],
        [
          84.0,
          378.0
        ],
        [
          82.0,
          376.0
        ],
        [
          78.0,
          374.0
        ],
        [
          73.0,
          373.0
        ],
        [
          63.0,
          366.0
        ],
        [
          53.0,
          361.0
        ],
        [
          51.0,
          361.0
        ],
        [
          44.0,
          357.0
        ],
        [
          42.0,
          357.0
        ],
        [
          36.0,
          354.0
        ],
        [
          34.0,
          352.0
        ],
        [
          31.0,
          352.0
        ],
        [
          28.0,
          358.0
        ]
      ],
      "group_id": null,
      "shape_type": "polygon",
      "flags": {}
    },
    {
      "label": "可乐",
      "text": "",
      "points": [
        [
          429.0,
          202.0
        ],
        [
          408.0,
          202.0
        ],
        [
          407.0,
          203.0
        ],
        [
          401.0,
          203.0
        ],
        [
          389.0,
          207.0
        ],
        [
          388.0,
          210.0
        ],
        [
          388.0,
          230.0
        ],
        [
          387.0,
          232.0
        ],
        [
          388.0,
          233.0
        ],
        [
          388.0,
          238.0
        ],
        [
          394.0,
          243.0
        ],
        [
          395.0,
          250.0
        ],
        [
          393.0,
          253.0
        ],
        [
          392.0,
          259.0
        ],
        [
          390.0,
          261.0
        ],
        [
          390.0,
          263.0
        ],
        [
          388.0,
          264.0
        ],
        [
          387.0,
          268.0
        ],
        [
          383.0,
          274.0
        ],
        [
          369.0,
          288.0
        ],
        [
          365.0,
          300.0
        ],
        [
          362.0,
          305.0
        ],
        [
          361.0,
          373.0
        ],
        [
          362.0,
          374.0
        ],
        [
          362.0,
          380.0
        ],
        [
          365.0,
          392.0
        ],
        [
          365.0,
          404.0
        ],
        [
          360.0,
          415.0
        ],
        [
          360.0,
          421.0
        ],
        [
          359.0,
          422.0
        ],
        [
          360.0,
          439.0
        ],
        [
          363.0,
          447.0
        ],
        [
          363.0,
          452.0
        ],
        [
          366.0,
          459.0
        ],
        [
          371.0,
          462.0
        ],
        [
          385.0,
          461.0
        ],
        [
          390.0,
          464.0
        ],
        [
          395.0,
          479.0
        ],
        [
          421.0,
          479.0
        ],
        [
          424.0,
          471.0
        ],
        [
          428.0,
          468.0
        ],
        [
          431.0,
          468.0
        ],
        [
          446.0,
          473.0
        ],
        [
          451.0,
          473.0
        ],
        [
          454.0,
          471.0
        ],
        [
          459.0,
          461.0
        ],
        [
          463.0,
          445.0
        ],
        [
          463.0,
          440.0
        ],
        [
          464.0,
          439.0
        ],
        [
          464.0,
          421.0
        ],
        [
          462.0,
          419.0
        ],
        [
          462.0,
          412.0
        ],
        [
          460.0,
          409.0
        ],
        [
          460.0,
          405.0
        ],
        [
          467.0,
          386.0
        ],
        [
          467.0,
          379.0
        ],
        [
          468.0,
          378.0
        ],
        [
          468.0,
          349.0
        ],
        [
          469.0,
          348.0
        ],
        [
          469.0,
          338.0
        ],
        [
          470.0,
          337.0
        ],
        [
          471.0,
          326.0
        ],
        [
          473.0,
          320.0
        ],
        [
          473.0,
          311.0
        ],
        [
          472.0,
          310.0
        ],
        [
          472.0,
          306.0
        ],
        [
          465.0,
          293.0
        ],
        [
          464.0,
          288.0
        ],
        [
          462.0,
          288.0
        ],
        [
          454.0,
          277.0
        ],
        [
          450.0,
          274.0
        ],
        [
          445.0,
          262.0
        ],
        [
          445.0,
          258.0
        ],
        [
          443.0,
          253.0
        ],
        [
          443.0,
          247.0
        ],
        [
          450.0,
          243.0
        ],
        [
          451.0,
          241.0
        ],
        [
          451.0,
          237.0
        ],
        [
          450.0,
          236.0
        ],
        [
          450.0,
          211.0
        ],
        [
          447.0,
          207.0
        ],
        [
          436.0,
          203.0
        ],
        [
          430.0,
          203.0
        ]
      ],
      "group_id": null,
      "shape_type": "polygon",
      "flags": {}
    },
    {
      "label": "旺旺雪饼",
      "text": "",
      "points": [
        [
          341.0,
          212.0
        ],
        [
          339.0,
          210.0
        ],
        [
          337.0,
          210.0
        ],
        [
          336.0,
          211.0
        ],
        [
          336.0,
          212.0
        ],
        [
          335.0,
          213.0
        ],
        [
          334.0,
          213.0
        ],
        [
          333.0,
          214.0
        ],
        [
          326.0,
          214.0
        ],
        [
          325.0,
          215.0
        ],
        [
          324.0,
          215.0
        ],
        [
          322.0,
          217.0
        ],
        [
          321.0,
          217.0
        ],
        [
          319.0,
          219.0
        ],
        [
          317.0,
          219.0
        ],
        [
          316.0,
          218.0
        ],
        [
          316.0,
          217.0
        ],
        [
          315.0,
          217.0
        ],
        [
          315.0,
          220.0
        ],
        [
          314.0,
          221.0
        ],
        [
          314.0,
          222.0
        ],
        [
          315.0,
          223.0
        ],
        [
          315.0,
          224.0
        ],
        [
          314.0,
          225.0
        ],
        [
          314.0,
          226.0
        ],
        [
          315.0,
          227.0
        ],
        [
          315.0,
          228.0
        ],
        [
          314.0,
          229.0
        ],
        [
          314.0,
          232.0
        ],
        [
          315.0,
          233.0
        ],
        [
          316.0,
          232.0
        ],
        [
          319.0,
          232.0
        ],
        [
          320.0,
          231.0
        ],
        [
          322.0,
          231.0
        ],
        [
          323.0,
          230.0
        ],
        [
          325.0,
          230.0
        ],
        [
          326.0,
          229.0
        ],
        [
          328.0,
          229.0
        ],
        [
          329.0,
          228.0
        ],
        [
          332.0,
          228.0
        ],
        [
          333.0,
          227.0
        ],
        [
          339.0,
          227.0
        ],
        [
          340.0,
          226.0
        ],
        [
          342.0,
          226.0
        ],
        [
          342.0,
          225.0
        ],
        [
          344.0,
          223.0
        ],
        [
          344.0,
          217.0
        ],
        [
          343.0,
          217.0
        ],
        [
          342.0,
          216.0
        ],
        [
          342.0,
          215.0
        ],
        [
          341.0,
          214.0
        ]
      ],
      "group_id": null,
      "shape_type": "polygon",
      "flags": {}
    },
    {
      "label": "旺旺雪饼",
      "text": "",
      "points": [
        [
          329.0,
          198.0
        ],
        [
          326.0,
          198.0
        ],
        [
          325.0,
          199.0
        ],
        [
          325.0,
          201.0
        ],
        [
          326.0,
          202.0
        ],
        [
          326.0,
          212.0
        ],
        [
          324.0,
          214.0
        ],
        [
          322.0,
          214.0
        ],
        [
          321.0,
          213.0
        ],
        [
          320.0,
          214.0
        ],
        [
          318.0,
          214.0
        ],
        [
          316.0,
          212.0
        ],
        [
          315.0,
          212.0
        ],
        [
          315.0,
          213.0
        ],
        [
          314.0,
          214.0
        ],
        [
          314.0,
          221.0
        ],
        [
          313.0,
          222.0
        ],
        [
          313.0,
          225.0
        ],
        [
          314.0,
          226.0
        ],
        [
          314.0,
          229.0
        ],
        [
          312.0,
          231.0
        ],
        [
          309.0,
          228.0
        ],
        [
          309.0,
          225.0
        ],
        [
          310.0,
          224.0
        ],
        [
          310.0,
          223.0
        ],
        [
          309.0,
          224.0
        ],
        [
          306.0,
          224.0
        ],
        [
          305.0,
          223.0
        ],
        [
          303.0,
          225.0
        ],
        [
          303.0,
          228.0
        ],
        [
          304.0,
          229.0
        ],
        [
          305.0,
          229.0
        ],
        [
          306.0,
          228.0
        ],
        [
          308.0,
          228.0
        ],
        [
          309.0,
          229.0
        ],
        [
          309.0,
          230.0
        ],
        [
          308.0,
          231.0
        ],
        [
          308.0,
          234.0
        ],
        [
          310.0,
          234.0
        ],
        [
          310.0,
          233.0
        ],
        [
          312.0,
          231.0
        ],
        [
          313.0,
          231.0
        ],
        [
          314.0,
          232.0
        ],
        [
          316.0,
          232.0
        ],
        [
          317.0,
          231.0
        ],
        [
          320.0,
          231.0
        ],
        [
          321.0,
          230.0
        ],
        [
          323.0,
          230.0
        ],
        [
          324.0,
          229.0
        ],
        [
          328.0,
          229.0
        ],
        [
          329.0,
          228.0
        ],
        [
          331.0,
          228.0
        ],
        [
          332.0,
          227.0
        ],
        [
          339.0,
          227.0
        ],
        [
          340.0,
          226.0
        ],
        [
          341.0,
          226.0
        ],
        [
          344.0,
          223.0
        ],
        [
          344.0,
          218.0
        ],
        [
          342.0,
          216.0
        ],
        [
          342.0,
          215.0
        ],
        [
          341.0,
          214.0
        ],
        [
          341.0,
          212.0
        ],
        [
          338.0,
          209.0
        ],
        [
          337.0,
          209.0
        ],
        [
          335.0,
          211.0
        ],
        [
          333.0,
          211.0
        ],
        [
          332.0,
          210.0
        ],
        [
          332.0,
          209.0
        ],
        [
          333.0,
          208.0
        ],
        [
          333.0,
          204.0
        ],
        [
          332.0,
          203.0
        ],
        [
          331.0,
          203.0
        ],
        [
          330.0,
          202.0
        ],
        [
          330.0,
          200.0
        ],
        [
          329.0,
          199.0
        ]
      ],
      "group_id": null,
      "shape_type": "polygon",
      "flags": {}
    },
    {
      "label": "旺旺雪饼",
      "text": "",
      "points": [
        [
          127.0,
          145.0
        ],
        [
          119.0,
          146.0
        ],
        [
          117.0,
          148.0
        ],
        [
          98.0,
          156.0
        ],
        [
          94.0,
          160.0
        ],
        [
          89.0,
          161.0
        ],
        [
          87.0,
          163.0
        ],
        [
          77.0,
          167.0
        ],
        [
          71.0,
          172.0
        ],
        [
          69.0,
          172.0
        ],
        [
          50.0,
          188.0
        ],
        [
          29.0,
          191.0
        ],
        [
          0.0,
          199.0
        ],
        [
          0.0,
          232.0
        ],
        [
          5.0,
          232.0
        ],
        [
          7.0,
          234.0
        ],
        [
          6.0,
          236.0
        ],
        [
          0.0,
          237.0
        ],
        [
          0.0,
          240.0
        ],
        [
          5.0,
          240.0
        ],
        [
          9.0,
          243.0
        ],
        [
          11.0,
          241.0
        ],
        [
          15.0,
          241.0
        ],
        [
          18.0,
          246.0
        ],
        [
          14.0,
          249.0
        ],
        [
          20.0,
          255.0
        ],
        [
          22.0,
          255.0
        ],
        [
          24.0,
          253.0
        ],
        [
          26.0,
          254.0
        ],
        [
          32.0,
          253.0
        ],
        [
          41.0,
          258.0
        ],
        [
          40.0,
          259.0
        ],
        [
          41.0,
          262.0
        ],
        [
          41.0,
          269.0
        ],
        [
          40.0,
          270.0
        ],
        [
          36.0,
          270.0
        ],
        [
          34.0,
          268.0
        ],
        [
          35.0,
          265.0
        ],
        [
          33.0,
          263.0
        ],
        [
          32.0,
          259.0
        ],
        [
          23.0,
          259.0
        ],
        [
          22.0,
          261.0
        ],
        [
          30.0,
          268.0
        ],
        [
          30.0,
          270.0
        ],
        [
          41.0,
          278.0
        ],
        [
          40.0,
          284.0
        ],
        [
          46.0,
          283.0
        ],
        [
          48.0,
          285.0
        ],
        [
          48.0,
          288.0
        ],
        [
          50.0,
          290.0
        ],
        [
          49.0,
          294.0
        ],
        [
          52.0,
          297.0
        ],
        [
          57.0,
          298.0
        ],
        [
          61.0,
          301.0
        ],
        [
          61.0,
          303.0
        ],
        [
          59.0,
          305.0
        ],
        [
          65.0,
          311.0
        ],
        [
          68.0,
          311.0
        ],
        [
          70.0,
          313.0
        ],
        [
          70.0,
          317.0
        ],
        [
          79.0,
          325.0
        ],
        [
          87.0,
          342.0
        ],
        [
          89.0,
          361.0
        ],
        [
          94.0,
          366.0
        ],
        [
          107.0,
          365.0
        ],
        [
          128.0,
          355.0
        ],
        [
          148.0,
          343.0
        ],
        [
          162.0,
          338.0
        ],
        [
          164.0,
          335.0
        ],
        [
          172.0,
          332.0
        ],
        [
          175.0,
          329.0
        ],
        [
          184.0,
          327.0
        ],
        [
          188.0,
          324.0
        ],
        [
          191.0,
          324.0
        ],
        [
          213.0,
          316.0
        ],
        [
          223.0,
          310.0
        ],
        [
          223.0,
          306.0
        ],
        [
          221.0,
          301.0
        ],
        [
          200.0,
          280.0
        ],
        [
          199.0,
          272.0
        ],
        [
          192.0,
          263.0
        ],
        [
          184.0,
          262.0
        ],
        [
          178.0,
          265.0
        ],
        [
          174.0,
          264.0
        ],
        [
          173.0,
          262.0
        ],
        [
          175.0,
          258.0
        ],
        [
          175.0,
          254.0
        ],
        [
          173.0,
          251.0
        ],
        [
          174.0,
          246.0
        ],
        [
          173.0,
          241.0
        ],
        [
          170.0,
          234.0
        ],
        [
          161.0,
          225.0
        ],
        [
          160.0,
          220.0
        ],
        [
          158.0,
          216.0
        ],
        [
          153.0,
          211.0
        ],
        [
          150.0,
          203.0
        ],
        [
          147.0,
          202.0
        ],
        [
          145.0,
          206.0
        ],
        [
          143.0,
          205.0
        ],
        [
          139.0,
          191.0
        ],
        [
          140.0,
          187.0
        ],
        [
          139.0,
          177.0
        ],
        [
          135.0,
          170.0
        ],
        [
          136.0,
          167.0
        ],
        [
          134.0,
          168.0
        ],
        [
          132.0,
          167.0
        ],
        [
          132.0,
          164.0
        ],
        [
          135.0,
          163.0
        ],
        [
          135.0,
          158.0
        ]
      ],
      "group_id": null,
      "shape_type": "polygon",
      "flags": {}
    }
  ],
  "imagePath": "..\\..\\images\\train\\trainin\\144.jpg",
  "imageData": null,
  "imageHeight": 480,
  "imageWidth": 640
}